.bumpversion.cfg
.readthedocs.yaml
CODE_OF_CONDUCT.md
CONTRIBUTING.md
LICENSE
MANIFEST.in
Makefile
README.md
demo.gif
pyproject.toml
setup.py
Stixx.egg-info/PKG-INFO
Stixx.egg-info/SOURCES.txt
Stixx.egg-info/dependency_links.txt
Stixx.egg-info/requires.txt
Stixx.egg-info/top_level.txt
docs/Makefile
docs/conf.py
docs/index.md
docs/make.bat
stixx/__init__.py
stixx/game.py
stixx/players.py
stixx/tests/test_game.py
stixx/tests/test_players.py