Metadata-Version: 2.1
Name: Stixx
Version: 0.1.2
Summary: A simple two-player video game.
Author-email: Mauricio Guerrero <mg4145@columbia.edu>
License: Copyright 2023 Mauricio Guerrero
Project-URL: repository, https://github.com/mg4145/stixx
Classifier: Development Status :: 2 - Pre-Alpha
Classifier: Programming Language :: Python :: Implementation :: CPython
Classifier: Programming Language :: Python :: Implementation :: PyPy
Classifier: Programming Language :: Python :: 3
Classifier: Programming Language :: Python :: 3.7
Classifier: Programming Language :: Python :: 3.8
Classifier: Programming Language :: Python :: 3.9
Classifier: Programming Language :: Python :: 3.10
Classifier: Programming Language :: Python :: 3.11
Requires-Python: >=3.9.15
Provides-Extra: develop
License-File: LICENSE
